pypkgs_cs/__init__.py
pypkgs_cs/pypkgs_cs.py
pypkgs_cs-0.1.0.dist-info/LICENSE
pypkgs_cs-0.1.0.dist-info/WHEEL
pypkgs_cs-0.1.0.dist-info/METADATA
pypkgs_cs-0.1.0.dist-info/RECORD
