Metadata-Version: 2.1
Name: pypkgs-cs
Version: 0.1.0
Summary: Python package to ease the pain of concatenating Pandas categoricals
License: MIT
Author: Cal Schafer
Author-email: schafer1@student.ubc.ca
Requires-Python: >=3.8,<4.0
Classifier: License :: OSI Approved :: MIT License
Classifier: Programming Language :: Python :: 3
Classifier: Programming Language :: Python :: 3.8
Classifier: Programming Language :: Python :: 3.9
Requires-Dist: pandas (>=1.2.2,<2.0.0)
